{
"type": "FeatureCollection",
"name": "ws",
"crs": { "type": "name", "properties": { "name": "urn:ogc:def:crs:OGC:1.3:CRS84" } },
"features": [
{ "type": "Feature", "properties": { "site": "Log Boom", "lat": "44.71760227", "lon": "-122.2448237" }, "geometry": { "type": "Point", "coordinates": [ -122.2448237, 44.71760227 ] } },
{ "type": "Feature", "properties": { "site": "Blowout", "lat": "44.67544396", "lon": "-122.1887626" }, "geometry": { "type": "Point", "coordinates": [ -122.1887626, 44.67544396 ] } },
{ "type": "Feature", "properties": { "site": "Heater", "lat": "44.69537557", "lon": "-122.2412653" }, "geometry": { "type": "Point", "coordinates": [ -122.2412653, 44.69537557 ] } }
]
}
